[
  {
    "ContainingType": "eBookStoreAPI.Presentation.Controllers.AuthController",
    "Method": "Login",
    "RelativePath": "api/Auth/login",
    "HttpMethod": "POST",
    "IsController": true,
    "Order": 0,
    "Parameters": [
      {
        "Name": "command",
        "Type": "eBookStoreAPI.Application.UserAuthentication.Command.Login.LoginUserCommand",
        "IsRequired": true
      }
    ],
    "ReturnTypes": [
      {
        "Type": "eBookStoreAPI.Application.ApiUtilities.Shared.ApiResponse\u00601[[System.String, System.Private.CoreLib, Version=8.0.0.0, Culture=neutral, PublicKeyToken=7cec85d7bea7798e]]",
        "MediaTypes": [
          "text/plain",
          "application/json",
          "text/json"
        ],
        "StatusCode": 200
      }
    ]
  },
  {
    "ContainingType": "eBookStoreAPI.Presentation.Controllers.AuthController",
    "Method": "Register",
    "RelativePath": "api/Auth/register",
    "HttpMethod": "POST",
    "IsController": true,
    "Order": 0,
    "Parameters": [
      {
        "Name": "command",
        "Type": "eBookStoreAPI.Application.UserAuthentication.Command.Register.RegisterUserCommand",
        "IsRequired": true
      }
    ],
    "ReturnTypes": [
      {
        "Type": "eBookStoreAPI.Application.ApiUtilities.Shared.ApiResponse\u00601[[System.Int32, System.Private.CoreLib, Version=8.0.0.0, Culture=neutral, PublicKeyToken=7cec85d7bea7798e]]",
        "MediaTypes": [
          "text/plain",
          "application/json",
          "text/json"
        ],
        "StatusCode": 200
      }
    ]
  },
  {
    "ContainingType": "eBookStoreAPI.Presentation.Controllers.BookController",
    "Method": "AddBook",
    "RelativePath": "api/Book",
    "HttpMethod": "POST",
    "IsController": true,
    "Order": 0,
    "Parameters": [
      {
        "Name": "command",
        "Type": "eBookStoreAPI.Application.Products.Command.AddBook.AddBookCommand",
        "IsRequired": true
      }
    ],
    "ReturnTypes": []
  },
  {
    "ContainingType": "eBookStoreAPI.Presentation.Controllers.BookController",
    "Method": "SearchBooks",
    "RelativePath": "api/Book/search",
    "HttpMethod": "GET",
    "IsController": true,
    "Order": 0,
    "Parameters": [
      {
        "Name": "query",
        "Type": "System.String",
        "IsRequired": false
      },
      {
        "Name": "pageNumber",
        "Type": "System.Int32",
        "IsRequired": false
      },
      {
        "Name": "pageSize",
        "Type": "System.Int32",
        "IsRequired": false
      }
    ],
    "ReturnTypes": []
  },
  {
    "ContainingType": "eCartStoreAPI.Presentation.Controllers.CartController",
    "Method": "AddToCart",
    "RelativePath": "api/Cart",
    "HttpMethod": "POST",
    "IsController": true,
    "Order": 0,
    "Parameters": [
      {
        "Name": "command",
        "Type": "eBookStoreAPI.Application.Products.Command.AddBook.AddToCartCommand",
        "IsRequired": true
      }
    ],
    "ReturnTypes": []
  },
  {
    "ContainingType": "eCartStoreAPI.Presentation.Controllers.CartController",
    "Method": "RemoveFromCart",
    "RelativePath": "api/Cart/{cartItemId}",
    "HttpMethod": "DELETE",
    "IsController": true,
    "Order": 0,
    "Parameters": [
      {
        "Name": "cartItemId",
        "Type": "System.Int32",
        "IsRequired": true
      }
    ],
    "ReturnTypes": []
  },
  {
    "ContainingType": "eCartStoreAPI.Presentation.Controllers.CartController",
    "Method": "Checkout",
    "RelativePath": "api/Cart/checkout",
    "HttpMethod": "POST",
    "IsController": true,
    "Order": 0,
    "Parameters": [
      {
        "Name": "command",
        "Type": "eBookStoreAPI.Application.Products.Command.AddBook.CheckoutCommand",
        "IsRequired": true
      }
    ],
    "ReturnTypes": []
  },
  {
    "ContainingType": "eCartStoreAPI.Presentation.Controllers.CartController",
    "Method": "GetPurchaseHistory",
    "RelativePath": "api/Cart/purchase-history",
    "HttpMethod": "GET",
    "IsController": true,
    "Order": 0,
    "Parameters": [
      {
        "Name": "pageNumber",
        "Type": "System.Int32",
        "IsRequired": false
      },
      {
        "Name": "pageSize",
        "Type": "System.Int32",
        "IsRequired": false
      }
    ],
    "ReturnTypes": []
  },
  {
    "ContainingType": "eCartStoreAPI.Presentation.Controllers.CartController",
    "Method": "ViewCarts",
    "RelativePath": "api/Cart/View-Cart",
    "HttpMethod": "GET",
    "IsController": true,
    "Order": 0,
    "Parameters": [
      {
        "Name": "userId",
        "Type": "System.Int32",
        "IsRequired": false
      },
      {
        "Name": "pageNumber",
        "Type": "System.Int32",
        "IsRequired": false
      },
      {
        "Name": "pageSize",
        "Type": "System.Int32",
        "IsRequired": false
      }
    ],
    "ReturnTypes": []
  }
]